setup.py
distributions_punya/Binomialdistribution.py
distributions_punya/Gaussiandistribution.py
distributions_punya/Generaldistribution.py
distributions_punya/__init__.py
distributions_punya.egg-info/PKG-INFO
distributions_punya.egg-info/SOURCES.txt
distributions_punya.egg-info/dependency_links.txt
distributions_punya.egg-info/not-zip-safe
distributions_punya.egg-info/top_level.txt